qclassify/__init__.py
qclassify/_version.py
qclassify/encoder.py
qclassify/encoding_circ.py
qclassify/postprocessing.py
qclassify/preprocessing.py
qclassify/proc_circ.py
qclassify/processor.py
qclassify/qclassifier.py
qclassify/training.py
qclassify/xor_example.py
qclassify-0.0.1.dev0.dist-info/METADATA
qclassify-0.0.1.dev0.dist-info/WHEEL
qclassify-0.0.1.dev0.dist-info/top_level.txt
qclassify-0.0.1.dev0.dist-info/RECORD
