Metadata-Version: 2.1
Name: qclassify
Version: 0.0.1.dev0
Summary: A Python framework for the variational quantum classifier
Home-page: https://github.com/zapatacomputing/QClassify
Author: caoyudong
Author-email: yudong@zapatacomputing.com
License: Apache-2.0
Platform: UNKNOWN
Requires-Python: >=3.6
Requires-Dist: jupyter
Requires-Dist: pyquil (>=2.0.0b1)
Requires-Dist: matplotlib
Requires-Dist: scipy
